Metadata-Version: 1.1
Name: opster
Version: 4.2
Summary: command line parsing speedster
Home-page: http://github.com/piranha/opster/
Author: Alexander Solovyov
Author-email: alexander@solovyov.net
License: BSD
Platform: any
Classifier: Environment :: Console
Classifier: Intended Audience :: Developers
Classifier: License :: OSI Approved :: BSD License
Classifier: Operating System :: OS Independent
Classifier: Programming Language :: Python
Classifier: Topic :: Software Development
